{
  "username": "4Furki4",
  "name": "Furkan Cengiz",
  "image": "https://github.com/Kiran1689/Awesome-Dev-Portfolios/assets/84590614/c0e6c612-2a3e-41c0-bde2-061da69944f0",
  "technologiesUsed": "Next.js, React, TypeScript, Next-Intl, TailwindCSS, NextUI, framer-motion, ts-particles, plaiceholder",
  "livePortfolioLink": "https://www.furkancengiz.software/",
  "githubRepoLink": "https://github.com/4Furki4/the-portfolio",
  "email": "muhammedcengiz1@gmail.com",
  "linkedin": "https://www.linkedin.com/in/furkancengizz/"
}
