{
    "username": "mittal-parth",
    "name": "Parth Mittal",
    "image": "https://github.com/Kiran1689/Awesome-Dev-Portfolios/assets/75929997/b50dc42d-9657-40bd-8109-dea1cc46fc40",
    "technologiesUsed": "ReactJS, TailwindCSS, ViteJS, Framer Motion, React Lottie, React Icons",
    "livePortfolioLink": "https://parthmittal.netlify.app/",
    "githubRepoLink": "https://github.com/mittal-parth/personal-portfolio",
    "email": "-",
    "linkedin": "https://www.linkedin.com/in/mittal-parth",
    "instagram": "https://www.instagram.com/mittalparth_",
    "x": "https://www.twitter.com/mittalparth_"
  }
